CamsMazes/__init__.py
CamsMazes/maze.py
CamsMazes/maze_visualizer.py
CamsMazes-1.0.10.dist-info/METADATA
CamsMazes-1.0.10.dist-info/WHEEL
CamsMazes-1.0.10.dist-info/top_level.txt
CamsMazes-1.0.10.dist-info/RECORD
