Metadata-Version: 2.1
Name: CamsMazes
Version: 1.0.10
Summary: Maze Generator and Solver using DFS
Author-email: Cameron Rolfe <cameronrolfedev@example.com>
Project-URL: Homepage, https://github.com/CameronRolfe/MazeGenerator
Classifier: Programming Language :: Python :: 3
Classifier: Operating System :: Microsoft :: Windows
Requires-Dist: Pillow
